Metadata-Version: 2.1
Name: PaxosDB
Version: 20240123
Summary: Highly Available key value store with atomic updates - Replicated and Strongly Consistent
Home-page: https://github.com/magicray/PaxosDB
Author: Bhupendra Singh
Author-email: bhsingh@gmail.com
Keywords: paxos,consistent,replicated,cluster,config
License-File: LICENSE
